test_aide/__init__.py
test_aide/_version.py
test_aide/classes.py
test_aide/equality.py
test_aide/functions.py
test_aide/pandas.py
test_aide-0.1.1.dist-info/LICENSE
test_aide-0.1.1.dist-info/METADATA
test_aide-0.1.1.dist-info/WHEEL
test_aide-0.1.1.dist-info/top_level.txt
test_aide-0.1.1.dist-info/RECORD
