Metadata-Version: 2.1
Name: test-aide
Version: 0.1.1
Summary: Package of helper functions to be used for unit testing
Home-page: UNKNOWN
Author: LV GI Data Science Team
Author-email: #DataSciencePackages@lv.co.uk
License: UNKNOWN
Platform: UNKNOWN
Classifier: Programming Language :: Python
Classifier: Programming Language :: Python :: 3
Classifier: Programming Language :: Python :: 3.6
Classifier: Programming Language :: Python :: 3.7
Classifier: Programming Language :: Python :: 3.8
Classifier: Operating System :: OS Independent
Classifier: License :: OSI Approved :: BSD License
Requires-Python: >=3.6
License-File: LICENSE
Requires-Dist: pytest (>=5.4.1)
Requires-Dist: pytest-mock (>=3.5.1)
